{
  "name": "random_name_182",
  "age": 81,
  "isEmployed": false,
  "salary": 39577,
  "hobbies": [
    "reading",
    "traveling",
    "sports"
  ],
  "address": {
    "street": "random_street_31",
    "city": "random_city_59",
    "zipcode": "89074"
  },
  "random_property_319": [
    true,
    "nested_object_limit",
    true,
    683
  ],
  "random_property_472": [
    643,
    "random_string_288",
    [
      "random_string_749",
      344,
      73
    ]
  ],
  "random_property_70": [
    561,
    133,
    "random_string_879",
    829
  ],
  "random_property_701": {
    "nested_property_928": [
      582,
      false
    ],
    "nested_property_233": "random_string_68",
    "nested_property_870": "nested_object_limit"
  }
}