{
  "name": "random_name_351",
  "age": 59,
  "isEmployed": true,
  "salary": 35285,
  "hobbies": [
    "reading",
    "traveling",
    "sports"
  ],
  "address": {
    "street": "random_street_90",
    "city": "random_city_16",
    "zipcode": "12525"
  },
  "random_property_303": "random_string_961",
  "random_property_142": {
    "nested_property_897": false,
    "nested_property_790": 825
  },
  "random_property_596": [
    [
      true,
      758,
      true,
      1,
      "random_string_280"
    ],
    [
      97,
      715,
      true,
      [
        [
          true,
          false,
          [
            [
              "random_string_928",
              "nested_object_limit",
              "random_string_642",
              true,
              [
                "nested_object_limit",
                743,
                "nested_object_limit"
              ]
            ],
            false,
            227,
            false,
            "nested_object_limit"
          ]
        ],
        "nested_object_limit"
      ]
    ]
  ]
}