{
  "name": "random_name_992",
  "age": 71,
  "isEmployed": false,
  "salary": 62350,
  "hobbies": [
    "reading",
    "traveling",
    "sports"
  ],
  "address": {
    "street": "random_street_8",
    "city": "random_city_45",
    "zipcode": "67839"
  },
  "random_property_251": true,
  "random_property_628": [
    false,
    [
      564,
      "nested_object_limit",
      686,
      325,
      [
        "nested_object_limit",
        84,
        "nested_object_limit",
        974
      ]
    ],
    [
      false,
      763,
      "random_string_419",
      [
        "random_string_353",
        "nested_object_limit"
      ],
      "random_string_393"
    ]
  ]
}